LICENSE
MANIFEST.in
README.rst
setup.py
microurl/__init__.py
microurl/bitly.py
microurl/google.py
microurl.egg-info/PKG-INFO
microurl.egg-info/SOURCES.txt
microurl.egg-info/dependency_links.txt
microurl.egg-info/requires.txt
microurl.egg-info/top_level.txt
microurl.egg-info/zip-safe