Metadata-Version: 1.0
Name: microurl
Version: 0.1.1
Summary: microurl is a python module to create minfied urls
Home-page: http://github.com/micropyramid/microurl
Author: Ashwin
Author-email: hello@micropyramid.com
License: GPL3
Keywords: Url minifier python library using google,bitly
Platform: UNKNOWN
